Metadata-Version: 2.1
Name: octodir
Version: 1.1.0
Summary: Tool for downloading directories from Github repositories
Home-page: https://github.com/Jalkhov/octodir
Author: Pedro Torcatt
Author-email: pedrotorcattsoto@gmail.com
Project-URL: Bug Reports, https://github.com/Jalkhov/octodir/issues
Project-URL: Source, https://github.com/Jalkhov/octodir/
Keywords: github directory download
Classifier: Development Status :: 5 - Production/Stable
Classifier: Programming Language :: Python :: 3
Classifier: Natural Language :: English
Classifier: Environment :: Console
Classifier: License :: OSI Approved :: MIT License
Requires-Python: >=3.0
License-File: LICENSE
